<?xml version="1.0" encoding="utf-8"?>
<openerp>
  <data>
    <record id="action_remove_customer_followers" model="ir.actions.server">
      <field name="name">Remove Customers from Followers on Sales Oders</field>
      <field name="model_id" ref="sale.model_sale_order"/>
      <field name="code">
record = model.browse(context['active_id'])
if (record.state not in ['draft', 'sent', 'cancel'] and
        not record.has_removed_auto_followers):
    cr.execute("""
        DELETE FROM mail_followers
        WHERE res_model='sale.order'
        AND partner_id NOT IN (
            SELECT partner_id FROM res_users WHERE "share"=false
        )
        AND res_id=%s
    """, [record.id])
    record.write({'has_removed_auto_followers': True})

      </field>
    </record>
    <record id="action_rule_disable_auto_follower" model="base.action.rule">
      <field name="name">Disable Auto Follower</field>
      <field name="model_id" ref="sale.model_sale_order"/>
      <field name="active">true</field>
      <field name="kind">on_write</field>
      <field name="server_action_ids"  eval="[(6, 0, [ref('spg_disable_auto_follower.action_remove_customer_followers')])]"/>
    </record>
  </data>
</openerp>
